CHANGELOG.md
LICENSE
discord/ext/paginators/__init__.py
discord/ext/paginators/callbacks.py
discord/ext/paginators/codeblocks.py
discord/ext/paginators/controller.py
discord/ext/paginators/paginators/__init__.py
discord/ext/paginators/paginators/base.py
discord/ext/paginators/paginators/embed.py
discord/ext/paginators/paginators/embeds.py
discord/ext/paginators/paginators/fields.py
discord/ext/paginators/paginators/partial.py
discord/ext/paginators/paginators/text.py
discord/ext/paginators/py.typed
discord/ext/paginators/types.py
discord_ext_paginators-0.1.0.dist-info/LICENSE
discord_ext_paginators-0.1.0.dist-info/METADATA
discord_ext_paginators-0.1.0.dist-info/WHEEL
discord_ext_paginators-0.1.0.dist-info/RECORD
