Metadata-Version: 2.1
Name: discord-ext-paginators
Version: 0.1.0
Summary: A discord.py extension for my collection of paginators.
Home-page: https://github.com/Axelancerr/discord-ext-paginators
License: MIT
Keywords: discord,discord.ext,discord.py
Author: Aaron Hennessey
Author-email: axelancerr@gmail.com
Requires-Python: >=3.11.0,<4.0.0
Classifier: Development Status :: 4 - Beta
Classifier: Environment :: Other Environment
Classifier: Framework :: AsyncIO
Classifier: Intended Audience :: Developers
Classifier: License :: OSI Approved :: MIT License
Classifier: Natural Language :: English
Classifier: Operating System :: OS Independent
Classifier: Programming Language :: Python :: 3
Classifier: Programming Language :: Python :: 3.11
Classifier: Programming Language :: Python :: Implementation :: CPython
Classifier: Topic :: Software Development
Classifier: Topic :: Software Development :: Libraries
Classifier: Topic :: Software Development :: Libraries :: Python Modules
Classifier: Typing :: Typed
Requires-Dist: aiohttp (>=3.8.0,<4.0.0)
Requires-Dist: discord-py (>=2.3.0,<3.0.0)
Requires-Dist: typing-extensions (>=4.6.0,<5.0.0)
Project-URL: Documentation, https://discord-ext-paginators.readthedocs.io/en/latest/
Project-URL: Discord, https://discord.com/invite/w9f6NkQbde
Project-URL: Issue Tracker, https://github.com/Axelancerr/discord-ext-paginators/issues
Project-URL: Repository, https://github.com/Axelancerr/discord-ext-paginators
